{
	"schemaVersion": 1,
	"id": "draaft",
	"version": "${version}",
	"name": "drAAft",
	"description": "Mod for Pac's awesome AA Event",
	"authors": [
		"Memerson",
		"PacManMVC"
	],
	"contact": {
		"homepage": "https://fabricmc.net/",
		"sources": "https://github.com/FabricMC/fabric-example-mod"
	},
	"license": "CC0-1.0",
	"icon": "assets/drAAft/icon.png",
	"environment": "*",
	"entrypoints": {
		"main": [
          "drAAft.drAAft"
		]
	},
	"mixins": [
		"drAAft.mixins.json"
	],
	"depends": {
		"fabricloader": ">=0.16.13",
		"minecraft": "~1.16.1",
		"java": ">=8"
	}
}